qurcol/__init__.py
qurcol/cli.py
qurcol/format.py
qurcol/read.py
qurcol/sql.py
qurcol/table.py
qurcol-1.0.0.dist-info/entry_points.txt
qurcol-1.0.0.dist-info/LICENSE
qurcol-1.0.0.dist-info/WHEEL
qurcol-1.0.0.dist-info/METADATA
qurcol-1.0.0.dist-info/RECORD
