Metadata-Version: 2.1
Name: qurcol
Version: 1.0.0
Summary: qurcol (as in 'query columnar ...') is a command line tool that enables its users to quickly explore the content of a file in a column-oriented storage format
Home-page: https://github.com/candidtim/qurcol
Keywords: qurcol
Author: Timur Rubeko
Author-email: timur@rubeko.com
Requires-Python: >=3.7,<4.0
Classifier: Programming Language :: Python :: 3
Classifier: Programming Language :: Python :: 3.7
Classifier: Programming Language :: Python :: 3.8
Requires-Dist: click (>=7.1.2,<8.0.0)
Requires-Dist: pyarrow (>=0.17.1,<0.18.0)
Requires-Dist: pytz (>=2020.1,<2021.0)
Requires-Dist: tabulate (>=0.8.7,<0.9.0)
Project-URL: Repository, https://github.com/candidtim/qurcol
